putali/__init__.py
putali-0.0.7.dist-info/LICENSE
putali-0.0.7.dist-info/METADATA
putali-0.0.7.dist-info/WHEEL
putali-0.0.7.dist-info/top_level.txt
putali-0.0.7.dist-info/RECORD
