Metadata-Version: 2.1
Name: putali
Version: 0.0.7
Summary: Extracting contact-info from the website homepage
Home-page: UNKNOWN
Author: Ujjawal Shah
Author-email: ujjawalshah360@gmail.com
License: UNKNOWN
Keywords: email,phone number,telephone,website,homepage,python
Platform: UNKNOWN
Classifier: Development Status :: 1 - Planning
Classifier: Intended Audience :: Developers
Classifier: Programming Language :: Python :: 3
Classifier: Operating System :: Unix
Classifier: Operating System :: MacOS :: MacOS X
Classifier: Operating System :: Microsoft :: Windows
License-File: LICENSE
Requires-Dist: requests
Requires-Dist: bs4
